transformer_in_transformer/__init__.py
transformer_in_transformer/tnt.py
transformer_in_transformer-0.1.2.dist-info/LICENSE
transformer_in_transformer-0.1.2.dist-info/METADATA
transformer_in_transformer-0.1.2.dist-info/WHEEL
transformer_in_transformer-0.1.2.dist-info/top_level.txt
transformer_in_transformer-0.1.2.dist-info/RECORD
